Metadata-Version: 2.1
Name: blogdomarcio-alphav-client-python
Version: 0.0.1
Summary: Consumo de API utilizando a ALPHA VANTAGE
Home-page: https://github.com/blogdomarcio/alphav_client_python
Author: Claudio Marcio
Author-email: blogdomarcio@live.com
License: MIT License
Keywords: Pacote
Platform: UNKNOWN
